cbeiauto/Bacillus_subtilis.part500.cds.all.fa
cbeiauto/__init__.py
cbeiauto/cbei/__init__.py
cbeiauto/cbei/autoCBEI.py
cbeiauto/cbei/cbei.py
cbeiauto/cbei/stat.py
cbeiauto-1.6.2.dist-info/LICENSE
cbeiauto-1.6.2.dist-info/METADATA
cbeiauto-1.6.2.dist-info/WHEEL
cbeiauto-1.6.2.dist-info/entry_points.txt
cbeiauto-1.6.2.dist-info/top_level.txt
cbeiauto-1.6.2.dist-info/RECORD
