Metadata-Version: 2.1
Name: cbeiauto
Version: 1.6.2
Summary: "autoCBEI.py" can calculate the potential CBEI loci of the target CDSs and perform statistics and plots.
Home-page: https://github.com/atlasbioinfo/CRISPR-CBEI/tree/master/autoCBEI
Author: Haopeng Yu
Author-email: atlasbioin4@gmail.com
License: Apache-2.0
Platform: UNKNOWN
Classifier: Programming Language :: Python :: 3
Classifier: License :: OSI Approved :: Apache Software License
Classifier: Operating System :: OS Independent
Requires-Python: >=3.6.0
Requires-Dist: biopython
Requires-Dist: matplotlib
